fuzzysyn/__init__.py
fuzzysyn-0.4.0.dist-info/LICENSE
fuzzysyn-0.4.0.dist-info/METADATA
fuzzysyn-0.4.0.dist-info/WHEEL
fuzzysyn-0.4.0.dist-info/RECORD
